flake8_plugin_utils-stubs/METADATA.toml
flake8_plugin_utils-stubs/__init__.pyi
flake8_plugin_utils-stubs/plugin.pyi
flake8_plugin_utils-stubs/utils/__init__.pyi
flake8_plugin_utils-stubs/utils/assertions.pyi
flake8_plugin_utils-stubs/utils/constants.pyi
flake8_plugin_utils-stubs/utils/equiv_nodes.pyi
types_flake8_plugin_utils-1.3.7.4.dist-info/METADATA
types_flake8_plugin_utils-1.3.7.4.dist-info/WHEEL
types_flake8_plugin_utils-1.3.7.4.dist-info/top_level.txt
types_flake8_plugin_utils-1.3.7.4.dist-info/RECORD
